MANIFEST.in
README.md
requirements.txt
setup.py
joker/__init__.py
joker/scraper/__init__.py
joker/scraper/browser.py
joker/scraper/brutal.py
joker/scraper/parser.py
joker_scraper.egg-info/PKG-INFO
joker_scraper.egg-info/SOURCES.txt
joker_scraper.egg-info/dependency_links.txt
joker_scraper.egg-info/namespace_packages.txt
joker_scraper.egg-info/not-zip-safe
joker_scraper.egg-info/requires.txt
joker_scraper.egg-info/top_level.txt